dotter/__init__.py
dotter/dotter.py
dotter-0.5.0.dist-info/DESCRIPTION.rst
dotter-0.5.0.dist-info/METADATA
dotter-0.5.0.dist-info/RECORD
dotter-0.5.0.dist-info/WHEEL
dotter-0.5.0.dist-info/metadata.json
dotter-0.5.0.dist-info/top_level.txt
