Metadata-Version: 2.0
Name: dotter
Version: 0.5.0
Summary: Dotter is a graphviz wrapper for Python 2 and 3
Home-page: https://github.com/paetzke/dotter
Author: Friedrich Paetzke
Author-email: paetzke@fastmail.fm
License: BSD
Platform: UNKNOWN
Classifier: Intended Audience :: Developers
Classifier: License :: OSI Approved :: BSD License
Classifier: Programming Language :: Python
Classifier: Programming Language :: Python :: 2
Classifier: Programming Language :: Python :: 2.7
Classifier: Programming Language :: Python :: 3
Classifier: Programming Language :: Python :: 3.3
Classifier: Programming Language :: Python :: Implementation :: CPython
Classifier: Programming Language :: Python :: Implementation :: PyPy
Classifier: Topic :: Software Development :: Libraries
Classifier: Topic :: Utilities
